featmf/__about__.py
featmf/__init__.py
featmf/templates.py
featmf/utilities.py
featmf/lfdd/__init__.py
featmf/lfdd/sift.py
featmf-0.1.1.dist-info/METADATA
featmf-0.1.1.dist-info/WHEEL
featmf-0.1.1.dist-info/licenses/LICENSE
featmf-0.1.1.dist-info/RECORD
