Metadata-Version: 2.1
Name: featmf
Version: 0.1.1
Summary: A Feature Matching Framework
Project-URL: Documentation, https://featmf.readthedocs.io/en/latest/
Project-URL: Bug Tracker, https://github.com/TheProjectsGuy/FeatMF/issues
Project-URL: Repository, https://github.com/TheProjectsGuy/FeatMF
Author-email: Avneesh Mishra <123avneesh+featmf@gmail.com>
License:                    GNU LESSER GENERAL PUBLIC LICENSE
License-File: LICENSE
Classifier: Development Status :: 4 - Beta
Classifier: License :: OSI Approved :: GNU Lesser General Public License v3 (LGPLv3)
Classifier: Operating System :: POSIX :: Linux
Classifier: Programming Language :: Python
Classifier: Programming Language :: Python :: 3
Classifier: Programming Language :: Python :: 3.7
Classifier: Programming Language :: Python :: 3.8
Classifier: Programming Language :: Python :: 3.9
Classifier: Programming Language :: Python :: 3.10
Classifier: Programming Language :: Python :: 3.11
Classifier: Programming Language :: Python :: Implementation :: CPython
Classifier: Programming Language :: Python :: Implementation :: PyPy
Requires-Python: >=3.7
